pysge/__init__.py
pysge/area.py
pysge/interface.py
pysge/monitor.py
pysge/pysge_worker.py
pysge/submitter.py
pysge/utils.py
pysge-0.2.5.data/scripts/pysge_worker.py
pysge-0.2.5.data/scripts/pysge_worker.sh
pysge-0.2.5.dist-info/LICENSE
pysge-0.2.5.dist-info/METADATA
pysge-0.2.5.dist-info/WHEEL
pysge-0.2.5.dist-info/top_level.txt
pysge-0.2.5.dist-info/RECORD
