Metadata-Version: 2.1
Name: pysge
Version: 0.2.5
Summary: python interface to submit functions to an SGE batch cluster
Home-page: UNKNOWN
Author: Shane Breeze
Author-email: sdb15@ic.ac.uk
License: UNKNOWN
Platform: UNKNOWN
Classifier: Programming Language :: Python :: 2
Classifier: Programming Language :: Python :: 3
Classifier: License :: OSI Approved :: MIT License
Classifier: Operating System :: OS Independent
Classifier: Topic :: Software Development :: Libraries :: Python Modules
Classifier: Topic :: Utilities
Classifier: Development Status :: 3 - Alpha
Requires-Dist: future (>=0.17.1)
Requires-Dist: tqdm (>=4.31.1)
Requires-Dist: subprocess32 (>=3.5.4)
Requires-Dist: dill (>=0.3.0)
